demo/__init__.py
demo/manage.py
demo/settings.py
demo/urls.py
demo/wsgi.py
django_djfiles-0.2.dist-info/DESCRIPTION.rst
django_djfiles-0.2.dist-info/METADATA
django_djfiles-0.2.dist-info/RECORD
django_djfiles-0.2.dist-info/WHEEL
django_djfiles-0.2.dist-info/metadata.json
django_djfiles-0.2.dist-info/top_level.txt
djfiles/__init__.py
djfiles/admin.py
djfiles/apps.py
djfiles/models.py
djfiles/urls.py
djfiles/views.py
djfiles/migrations/0001_initial.py
djfiles/migrations/__init__.py
