Metadata-Version: 2.0
Name: django-djfiles
Version: 0.2
Summary: A simple Django app to upload files via admin panel.
Home-page: https://github.com/luminousmen/djfiles
Author: Bobrov Kirill
Author-email: miaplanedo@gmail.com
License: BSD License
Platform: UNKNOWN
Classifier: Framework :: Django
Classifier: Intended Audience :: Developers
Classifier: License :: OSI Approved :: BSD License
Classifier: Operating System :: OS Independent
Classifier: Programming Language :: Python
Classifier: Programming Language :: Python :: 2
Classifier: Programming Language :: Python :: 3
Classifier: Programming Language :: Python :: 3.4
Classifier: Programming Language :: Python :: 3.5
Classifier: Topic :: Internet :: WWW/HTTP
Classifier: Topic :: Internet :: WWW/HTTP :: Dynamic Content
Requires-Dist: slugify
